README.md
setup.cfg
setup.py
pyarmet/__init__.py
pyarmet/entry_points.py
pyarmet.egg-info/PKG-INFO
pyarmet.egg-info/SOURCES.txt
pyarmet.egg-info/dependency_links.txt
pyarmet.egg-info/entry_points.txt
pyarmet.egg-info/not-zip-safe
pyarmet.egg-info/requires.txt
pyarmet.egg-info/top_level.txt