Metadata-Version: 2.1
Name: pyarmet
Version: 0.0.2
Summary: PyArmet: This is a package for performing federated learning computations
Home-page: https://www.devron.ai/products
Author: Sidhartha Roy, Eddie de Leon, Shashank Pathak
Author-email: sidhartha@devron.ai
License: Devron
Keywords: python,armet,sklearn,federated learning
Platform: UNKNOWN
Classifier: Development Status :: 3 - Alpha
Classifier: Intended Audience :: Developers
Classifier: Programming Language :: Python :: 3.7
Requires-Python: >=3.6.*
